Dtls-1.2.3.dist-info/DESCRIPTION.rst
Dtls-1.2.3.dist-info/METADATA
Dtls-1.2.3.dist-info/RECORD
Dtls-1.2.3.dist-info/WHEEL
Dtls-1.2.3.dist-info/metadata.json
Dtls-1.2.3.dist-info/top_level.txt
dtls/ChangeLog
dtls/LICENSE
dtls/NOTICE
dtls/README.md
dtls/__init__.py
dtls/err.py
dtls/openssl.py
dtls/patch.py
dtls/sslconnection.py
dtls/tlock.py
dtls/util.py
dtls/wrapper.py
dtls/x509.py
dtls/demux/__init__.py
dtls/demux/osnet.py
dtls/demux/router.py
dtls/test/__init__.py
dtls/test/echo_seq.py
dtls/test/makecerts
dtls/test/makecerts_ec.bat
dtls/test/openssl_ca.cnf
dtls/test/openssl_server.cnf
dtls/test/rl.py
dtls/test/simple_client.py
dtls/test/test_perf.py
dtls/test/unit.py
dtls/test/unit_wrapper.py
dtls/test/certs/badcert.pem
dtls/test/certs/badkey.pem
dtls/test/certs/ca-cert.pem
dtls/test/certs/ca-cert_ec.pem
dtls/test/certs/keycert.pem
dtls/test/certs/keycert_ec.pem
dtls/test/certs/nullcert.pem
dtls/test/certs/server-cert.pem
dtls/test/certs/server-cert_ec.pem
dtls/test/certs/wrongcert.pem
dtls/test/certs/yahoo-cert.pem
