Metadata-Version: 2.0
Name: Dtls
Version: 1.2.3
Summary: Python Datagram Transport Layer Security
Home-page: https://github.com/rbit/pydtls
Author: Ray Brown
Author-email: code@liquibits.com
License: Apache-2.0
Platform: UNKNOWN
Classifier: Development Status :: 5 - Production/Stable
Classifier: Intended Audience :: Developers
Classifier: Topic :: Security :: Cryptography
Classifier: Topic :: Software Development :: Libraries :: Python Modules
Classifier: License :: OSI Approved :: Apache Software License
Classifier: Operating System :: POSIX :: Linux
Classifier: Operating System :: Microsoft :: Windows
Classifier: Programming Language :: Python :: 2.7
